{
  "globalStyle": {
    "navigationStyle": "custom",
    "navigationBarBackgroundColor": "@navBgColor",
    "navigationBarTextStyle": "@navTxtStyle",
    "navigationBarTitleText": "Beta Tool",
    "backgroundColor": "@bgColor",
    "backgroundTextStyle": "@bgTxtStyle",
    "backgroundColorTop": "@bgColorTop",
    "backgroundColorBottom": "@bgColorBottom",
    "enablePullDownRefresh": false,
    "onReachBottomDistance": 50,
    "animationType": "pop-in",
    "animationDuration": 300
  },
  "pages": [
    // #ifdef H5 || MP-WEIXIN
    {
      "path": "pages/index/index",
      "type": "home",
      "name": "home",
      "layout": "tabbar",
      "style": {
        "navigationBarTitleText": "首页"
      }
    },
    // #endif
    {
      "path": "pages/about/index",
      "type": "page",
      "name": "about",
      "layout": "tabbar",
      "style": {
        "navigationBarTitleText": "设置"
      }
    }
  ],
  "subPackages": [
    {
      "root": "subPages",
      "pages": [
        // #ifdef H5 || MP-WEIXIN
        {
          "path": "etf/detail",
          "type": "page",
          "name": "etf-detail",
          "layout": "default",
          "style": {
            "navigationBarTitleText": "ETF详情",
            "navigationBarBackgroundColor": "#f8fafc",
            "navigationBarTextStyle": "black"
          }
        },
        // #endif
        {
          "path": "etf/index",
          "type": "page",
          "name": "etf",
          "layout": "default",
          "style": {
            "navigationBarTitleText": "ETF估值表"
          }
        },
        {
          "path": "etf/performance",
          "type": "page",
          "name": "etf-performance",
          "layout": "default",
          "style": {
            "navigationBarTitleText": "业绩走势",
            "navigationBarBackgroundColor": "#f8fafc",
            "navigationBarTextStyle": "black"
          }
        },
        {
          "path": "etf/profile",
          "type": "page",
          "name": "etf-profile",
          "layout": "default",
          "style": {
            "navigationBarTitleText": "基金简况"
          }
        },
        {
          "path": "shixi-guide/asset-detail",
          "type": "page",
          "name": "asset-detail",
          "layout": "default",
          "style": {
            "navigationBarTitleText": "指数详情"
          }
        },
        {
          "path": "shixi-guide/index-list",
          "type": "page",
          "name": "dividend-index-list",
          "layout": "default",
          "style": {
            "navigationBarTitleText": "红利指数浏览器"
          }
        },
        {
          "path": "tamp/demo",
          "type": "page",
          "name": "tamp-demo",
          "layout": "default",
          "style": {
            "navigationBarTitleText": "店铺详情"
          }
        },
        {
          "path": "tamp/index",
          "type": "page",
          "name": "tamp",
          "layout": "default",
          "style": {
            "navigationBarTitleText": "TAMP"
          }
        },
        {
          "path": "tamp/marketing",
          "type": "page",
          "name": "tamp-marketing",
          "layout": "default",
          "style": {
            "navigationBarTitleText": "产品介绍"
          }
        }
      ]
    }
  ],
  "tabBar": {
    "custom": true,
    "customize": true,
    "overlay": true,
    "height": "0",
    "color": "@tabColor",
    "selectedColor": "@tabSelectedColor",
    "backgroundColor": "@tabBgColor",
    "borderStyle": "@tabBorderStyle",
    "list": [
      // GENERATED BY UNI-PAGES, PLATFORM: H5 || MP-WEIXIN
      {
        "pagePath": "pages/index/index"
      },
      {
        "pagePath": "pages/about/index"
      }
    ]
  }
}
